magicapp_common_assets/__init__.py
magicapp_common_assets/data_models/__init__.py
magicapp_common_assets/data_models/api_dtos.py
magicapp_common_assets/data_models/documents.py
magicapp_common_assets/data_models/vectors.py
magicapp_common_assets/dto_to_doc.py
magicapp_common_assets-0.0.9.dist-info/LICENSE
magicapp_common_assets-0.0.9.dist-info/METADATA
magicapp_common_assets-0.0.9.dist-info/WHEEL
magicapp_common_assets-0.0.9.dist-info/RECORD
